{
	"format_version": "1.9.0",
	"credit": "Made with Blockbench",
	"texture_size": [32, 32],
	"textures": {
		"0": "vsyncmod:item/mukisane1",
		"1": "vsyncmod:item/mukisane2",
		"2": "vsyncmod:item/mukisane3",
		"particle": "vsyncmod:item/mukisane1"
	},
	"elements": [
		{
			"from": [7.7, -9.5, 7.1],
			"to": [8.3, 0, 8.9],
			"rotation": {"angle": 0, "axis": "y", "origin": [7, -2, 7]},
			"faces": {
				"north": {"uv": [4, 0, 4.8125, 10], "texture": "#0"},
				"east": {"uv": [0, 0, 1.625, 10], "texture": "#0"},
				"south": {"uv": [5, 0, 5.8125, 10], "texture": "#0"},
				"west": {"uv": [2, 0, 3.625, 10], "texture": "#0"},
				"up": {"uv": [6.8125, 1.625, 6, 0], "texture": "#0"},
				"down": {"uv": [6.8125, 2, 6, 3.625], "texture": "#0"}
			}
		},
		{
			"from": [7.85, 0, 7.2],
			"to": [8.15, 1, 8.8],
			"rotation": {"angle": 0, "axis": "y", "origin": [7, 6, 7]},
			"faces": {
				"north": {"uv": [4, 8, 5.25, 12], "texture": "#1"},
				"east": {"uv": [0, 0, 6.5, 4], "texture": "#1"},
				"south": {"uv": [8, 8, 9.25, 12], "texture": "#1"},
				"west": {"uv": [0, 4, 6.5, 8], "texture": "#1"},
				"up": {"uv": [1.25, 14.5, 0, 8], "texture": "#1"},
				"down": {"uv": [9.25, 0, 8, 6.5], "texture": "#1"}
			}
		},
		{
			"from": [7.875, 1, 8.3],
			"to": [8.125, 30.235, 8.78],
			"rotation": {"angle": 0, "axis": "y", "origin": [7.1, 2.1, 7]},
			"faces": {
				"north": {"uv": [4, 0, 4.125, 14.625], "texture": "#2"},
				"east": {"uv": [0, 0, 0.23438, 14.625], "texture": "#2"},
				"south": {"uv": [4.5, 0, 4.625, 14.625], "texture": "#2"},
				"west": {"uv": [0.5, 0, 0.73438, 14.625], "texture": "#2"},
				"up": {"uv": [10.125, 4.23438, 10, 4], "texture": "#2"},
				"down": {"uv": [10.125, 4.5, 10, 4.73438], "texture": "#2"}
			}
		},
		{
			"from": [7.9, 1, 8],
			"to": [8.1, 29.5, 8.31],
			"rotation": {"angle": 0, "axis": "y", "origin": [7, 2.1, 6.5]},
			"faces": {
				"north": {"uv": [5, 0, 5.09375, 14.25], "texture": "#2"},
				"east": {"uv": [2, 0, 2.15625, 14.25], "texture": "#2"},
				"south": {"uv": [5.5, 0, 5.59375, 14.25], "texture": "#2"},
				"west": {"uv": [2.5, 0, 2.65625, 14.25], "texture": "#2"},
				"up": {"uv": [10.09375, 8.15625, 10, 8], "texture": "#2"},
				"down": {"uv": [10.09375, 8.5, 10, 8.65625], "texture": "#2"}
			}
		},
		{
			"from": [7.925, 1, 7.735],
			"to": [8.075, 28.85, 8.005],
			"rotation": {"angle": 0, "axis": "y", "origin": [8, 15, 7.75]},
			"faces": {
				"north": {"uv": [7, 0, 7.07813, 13.92188], "texture": "#2"},
				"east": {"uv": [3, 0, 3.14063, 13.92188], "texture": "#2"},
				"south": {"uv": [7.5, 0, 7.57813, 13.92188], "texture": "#2"},
				"west": {"uv": [3.5, 0, 3.64063, 13.92188], "texture": "#2"},
				"up": {"uv": [10.57813, 0.64063, 10.5, 0.5], "texture": "#2"},
				"down": {"uv": [10.57813, 1, 10.5, 1.14063], "texture": "#2"}
			}
		},
		{
			"from": [7.925, 28.83, 7.852],
			"to": [8.075, 29.53, 8.152],
			"rotation": {"angle": 22.5, "axis": "x", "origin": [8, 29.15, 7.85]},
			"faces": {
				"north": {"uv": [10, 5, 10.07813, 5.34375], "texture": "#2"},
				"east": {"uv": [10, 2, 10.15625, 2.34375], "texture": "#2"},
				"south": {"uv": [10, 5.5, 10.07813, 5.84375], "texture": "#2"},
				"west": {"uv": [10, 2.5, 10.15625, 2.84375], "texture": "#2"},
				"up": {"uv": [10.07813, 10.15625, 10, 10], "texture": "#2"},
				"down": {"uv": [10.57813, 0, 10.5, 0.15625], "texture": "#2"}
			}
		},
		{
			"from": [7.95, 1, 7.4],
			"to": [8.05, 28.05, 7.75],
			"rotation": {"angle": 0, "axis": "y", "origin": [7, 2.1, 5.7]},
			"faces": {
				"north": {"uv": [8, 0, 8.04688, 13.53125], "texture": "#2"},
				"east": {"uv": [1, 0, 1.17188, 13.53125], "texture": "#2"},
				"south": {"uv": [8.5, 0, 8.54688, 13.53125], "texture": "#2"},
				"west": {"uv": [1.5, 0, 1.67188, 13.53125], "texture": "#2"},
				"up": {"uv": [10.54688, 1.67188, 10.5, 1.5], "texture": "#2"},
				"down": {"uv": [10.54688, 2, 10.5, 2.17188], "texture": "#2"}
			}
		},
		{
			"from": [7.95, 28, 7.545],
			"to": [8.05, 28.89, 7.895],
			"rotation": {"angle": 22.5, "axis": "x", "origin": [8, 28.4, 7.575]},
			"faces": {
				"north": {"uv": [10, 7, 10.04688, 7.4375], "texture": "#2"},
				"east": {"uv": [10, 0, 10.17188, 0.4375], "texture": "#2"},
				"south": {"uv": [10, 7.5, 10.04688, 7.9375], "texture": "#2"},
				"west": {"uv": [10, 0.5, 10.17188, 0.9375], "texture": "#2"},
				"up": {"uv": [10.54688, 2.67188, 10.5, 2.5], "texture": "#2"},
				"down": {"uv": [10.54688, 3, 10.5, 3.17188], "texture": "#2"}
			}
		},
		{
			"from": [7.975, 1, 7.21],
			"to": [8.025, 27.6, 7.4],
			"rotation": {"angle": 0, "axis": "y", "origin": [7, 2.1, 5.4]},
			"faces": {
				"north": {"uv": [9, 0, 9.03125, 13.29688], "texture": "#2"},
				"east": {"uv": [6, 0, 6.09375, 13.29688], "texture": "#2"},
				"south": {"uv": [9.5, 0, 9.53125, 13.29688], "texture": "#2"},
				"west": {"uv": [6.5, 0, 6.59375, 13.29688], "texture": "#2"},
				"up": {"uv": [10.53125, 4.59375, 10.5, 4.5], "texture": "#2"},
				"down": {"uv": [10.53125, 5, 10.5, 5.09375], "texture": "#2"}
			}
		},
		{
			"from": [7.975, 27.56, 7.275],
			"to": [8.025, 28.06, 7.465],
			"rotation": {"angle": 22.5, "axis": "x", "origin": [8, 27.75, 7.305]},
			"faces": {
				"north": {"uv": [10.5, 3.5, 10.53125, 3.75], "texture": "#2"},
				"east": {"uv": [10, 6, 10.09375, 6.25], "texture": "#2"},
				"south": {"uv": [10.5, 4, 10.53125, 4.25], "texture": "#2"},
				"west": {"uv": [10, 6.5, 10.09375, 6.75], "texture": "#2"},
				"up": {"uv": [10.53125, 5.59375, 10.5, 5.5], "texture": "#2"},
				"down": {"uv": [10.53125, 6, 10.5, 6.09375], "texture": "#2"}
			}
		},
		{
			"from": [7.9, 29.46, 8.108],
			"to": [8.1, 30.26, 8.408],
			"rotation": {"angle": 22.5, "axis": "x", "origin": [8, 29.75, 8.15]},
			"faces": {
				"north": {"uv": [10, 3, 10.09375, 3.40625], "texture": "#2"},
				"east": {"uv": [10, 1, 10.15625, 1.40625], "texture": "#2"},
				"south": {"uv": [10, 3.5, 10.09375, 3.90625], "texture": "#2"},
				"west": {"uv": [10, 1.5, 10.15625, 1.90625], "texture": "#2"},
				"up": {"uv": [10.09375, 9.15625, 10, 9], "texture": "#2"},
				"down": {"uv": [10.09375, 9.5, 10, 9.65625], "texture": "#2"}
			}
		}
	],
	"display": {
		"thirdperson_righthand": {
			"translation": [0, 8.5, 0.75],
			"scale": [0.9, 0.85, 0.7]
		},
		"thirdperson_lefthand": {
			"translation": [0, 8.5, 0.75],
			"scale": [0.9, 0.85, 0.7]
		},
		"ground": {
			"translation": [0, 13.25, 0]
		},
		"gui": {
			"rotation": [0, -90, 0],
			"translation": [0, -0.75, 0],
			"scale": [0.4, 0.4, 0.5]
		},
		"fixed": {
			"rotation": [0, 90, 0],
			"translation": [0, -1, 0],
			"scale": [0.5, 0.5, 0.5]
		}
	},
	"groups": [
		{
			"name": "mukisane",
			"origin": [8, 8, 8],
			"color": 0,
			"children": [
				{
					"name": "hand",
					"origin": [8, 8, 8],
					"color": 0,
					"children": [0]
				},
				{
					"name": "guard",
					"origin": [8, 8, 8],
					"color": 0,
					"children": [1]
				},
				{
					"name": "sword",
					"origin": [8, 8, 8],
					"color": 0,
					"children": [2, 3, 4, 5, 6, 7, 8, 9, 10]
				}
			]
		}
	]
}